mds_mcp/__init__.py
mds_mcp/logger.py
mds_mcp/main.py
mds_mcp/provider/__init__.py
mds_mcp/provider/base.py
mds_mcp/provider/huggingface_provider.py
mds_mcp/services/__init__.py
mds_mcp/services/mcp_service.py
mds_mcp-0.1.3.dist-info/METADATA
mds_mcp-0.1.3.dist-info/WHEEL
mds_mcp-0.1.3.dist-info/entry_points.txt
mds_mcp-0.1.3.dist-info/licenses/LICENSE
mds_mcp-0.1.3.dist-info/RECORD
