Metadata-Version: 2.4
Name: mds-mcp
Version: 0.1.3
Summary: Model Cache Server - MCP server for downloading and caching ML models and datasets
Project-URL: Homepage, https://github.com/kk-xuhj/mds-mcp
Project-URL: Repository, https://github.com/kk-xuhj/mds-mcp
Project-URL: Bug Tracker, https://github.com/kk-xuhj/mds-mcp/issues
Project-URL: Documentation, https://github.com/kk-xuhj/mds-mcp#readme
Author-email: Kirk Xu <adolfxuhj@163.com>
Maintainer-email: Kirk Xu <adolfxuhj@163.com>
License: MIT
License-File: LICENSE
Keywords: datasets,huggingface,machine-learning,mcp,model-cache
Classifier: Development Status :: 4 - Beta
Classifier: Intended Audience :: Developers
Classifier: License :: OSI Approved :: MIT License
Classifier: Operating System :: OS Independent
Classifier: Programming Language :: Python :: 3
Classifier: Programming Language :: Python :: 3.11
Classifier: Programming Language :: Python :: 3.12
Classifier: Topic :: Scientific/Engineering :: Artificial Intelligence
Classifier: Topic :: Software Development :: Libraries :: Python Modules
Requires-Python: >=3.11
Requires-Dist: aiohttp>=3.12.13
Requires-Dist: colorama>=0.4.6
Requires-Dist: datasets>=2.0.0
Requires-Dist: fastmcp>=0.1.0
Requires-Dist: huggingface-hub>=0.20.0
Requires-Dist: python-dotenv>=1.0.0
Requires-Dist: sentry-sdk>=2.0.0
Requires-Dist: torch>=2.7.1
Requires-Dist: transformers>=4.30.0
Provides-Extra: dev
Requires-Dist: black>=23.0.0; extra == 'dev'
Requires-Dist: flake8>=6.0.0; extra == 'dev'
Requires-Dist: isort>=5.0.0; extra == 'dev'
Requires-Dist: mypy>=1.0.0; extra == 'dev'
Requires-Dist: pre-commit>=3.0.0; extra == 'dev'
Requires-Dist: pytest-cov>=4.0.0; extra == 'dev'
Requires-Dist: pytest>=8.4.1; extra == 'dev'
Requires-Dist: types-colorama>=0.4.15; extra == 'dev'
